tcxfile/__init__.py
tcxfile/tcx.py
tcxfile/version_info.py
tcxfile-1.0.4.dist-info/LICENSE
tcxfile-1.0.4.dist-info/METADATA
tcxfile-1.0.4.dist-info/WHEEL
tcxfile-1.0.4.dist-info/top_level.txt
tcxfile-1.0.4.dist-info/RECORD
