Metadata-Version: 2.1
Name: tcxfile
Version: 1.0.4
Summary: Read and write Tcx format files.
Home-page: https://github.com/tcgoetz/Tcx
Author: Tom Goetz
License: UNKNOWN
Platform: UNKNOWN
Classifier: License :: OSI Approved :: GNU General Public License v2 (GPLv2)
Classifier: Programming Language :: Python :: 3
Classifier: Operating System :: OS Independent
Requires-Python: >=3.0
License-File: LICENSE
